topsis/Chahat_102203637.py
topsis/__init__.py
Topsis_Chahat_102203637-0.1.0.dist-info/METADATA
Topsis_Chahat_102203637-0.1.0.dist-info/WHEEL
Topsis_Chahat_102203637-0.1.0.dist-info/entry_points.txt
Topsis_Chahat_102203637-0.1.0.dist-info/top_level.txt
Topsis_Chahat_102203637-0.1.0.dist-info/RECORD
