Metadata-Version: 2.1
Name: Topsis-Chahat-102203637
Version: 0.1.0
Summary: A Python package to implement the TOPSIS method for multi-criteria decision analysis.
Home-page: https://github.com/Chahat-05/Topsis-Chahat-102203637.git
Author: Chahat
Author-email: cverma_be22@thapar.edu
License: MIT
Classifier: Programming Language :: Python :: 3
Classifier: License :: OSI Approved :: MIT License
Classifier: Operating System :: OS Independent
Classifier: Programming Language :: Python :: 3 :: Only
Requires-Dist: pandas
Requires-Dist: numpy
